{
  "tag": 123231,
  "tag2": 12344,
  "label": "Label",
  "class": "TestClass",
  "mac_src": "sd:as:as:11",
  "mac_dst": "sd:12:33:44",
  "vlan": 123232131,
  "cos": 12123,
  "etype": "Test",
  "peer_ip_src": "12.3.4.5",
  "iface_in": 12312344,
  "iface_out": 1231441,
  "ip_src": "12.2.3.4",
  "net_src": "23.12.33.4",
  "ip_dst": "23.31.23.4",
  "net_dst": "21.34.5.66",
  "mask_src": 500,
  "mask_dst": 700,
  "port_src": 8080,
  "port_dst": 9191,
  "tcp_flags": "fss",
  "ip_proto": "photo.jpeg",
  "tos": 12312,
  "sampling_rate": 1231,
  "post_nat_ip_src": "5.2.4.5",
  "post_nat_ip_dst": "6.1.2.3",
  "post_nat_port_src": 9129,
  "post_nat_port_dst": 2222,
  "nat_event": 222,
  "mpls_label_top": 12313,
  "mpls_label_bottom": 12223,
  "mpls_stack_depth": 4444,
  "timestamp_start": "12-12-2020 T 14:10:00",
  "timestamp_end": "22-12-2020 T 14:10:00",
  "timestamp_arrival": "22-12-2020 T 14:10:00",
  "export_proto_seqno": 1233,
  "export_proto_version": 10,
  "custom_primitives": {
    "primitive": "valuePrimitive"
  },
  "stamp_inserted": null,
  "stamp_updated": null,
  "packets": null,
  "flows": null,
  "bytes": null,
  "writer_id": "testId"
}